[
	{
		"author": "Dinesh",  
		"books" : [ 
					{
						"name": "Dinesh book1 Name",
						"year": "1991",
						"publisher" : "Dinesh Book1 publisher",
						"isbn" : "Dinesh Book1 ISBN",
						"cost" : "10.50"
					},
					{
						"name": "Dinesh book2 Name",
						"year": "2001",
						"publisher" : "Dinesh Book2 publisher",
						"isbn" : "Dinesh Book2 ISBN",
						"cost" : "20.99"
					},
					{
						"name": "Dinesh book3 Name",
						"year": "2011",
						"publisher" : "Dinesh Book3 publisher",
						"isbn" : "Dinesh Book3 ISBN",
						"cost" : "15.75"
					}
				]
	},
	{
		"author": "Soumya",  
		"books" : [ 
					{
						"name": "Soumya book1 Name",
						"year": "1991",
						"publisher" : "Soumya Book1 publisher",
						"isbn" : "Soumya Book1 ISBN",
						"cost" : "10.50"
					},
					{
						"name": "Soumya book2 Name",
						"year": "2002",
						"publisher" : "Soumya Book2 publisher",
						"isbn" : "Soumya Book2 ISBN",
						"cost" : "21.99"
					},
					{
						"name": "Soumya book3 Name",
						"year": "2012",
						"publisher" : "Soumya Book3 publisher",
						"isbn" : "Soumya Book3 ISBN",
						"cost" : "16.75"
					}
				]
	},
	{
		"author": "Harry",  
		"books" : [ 
					{
						"name": "Harry book1 Name",
						"year": "1991",
						"publisher" : "Harry Book1 publisher",
						"isbn" : "Harry Book1 ISBN",
						"cost" : "10.50"
					},
					{
						"name": "Harry book2 Name",
						"year": "2003",
						"publisher" : "Harry Book2 publisher",
						"isbn" : "Harry Book2 ISBN",
						"cost" : "22.99"
					},
					{
						"name": "Harry book3 Name",
						"year": "2013",
						"publisher" : "Harry Book3 publisher",
						"isbn" : "Harry Book3 ISBN",
						"cost" : "17.75"
					}
				]
	},
	{
		"author": "Alvin",  
		"books" : [ 
					{
						"name": "Alvin book1 Name",
						"year": "1991",
						"publisher" : "Alvin Book1 publisher",
						"isbn" : "Alvin Book1 ISBN",
						"cost" : "10.50"
					},
					{
						"name": "Alvin book2 Name",
						"year": "2004",
						"publisher" : "Alvin Book2 publisher",
						"isbn" : "Alvin Book2 ISBN",
						"cost" : "23.99"
					},
					{
						"name": "Alvin book3 Name",
						"year": "2014",
						"publisher" : "Alvin Book3 publisher",
						"isbn" : "Alvin Book3 ISBN",
						"cost" : "18.75"
					}
				]
	}
]